src/__init__.py
src/core.py
this_me-0.1.0.dist-info/licenses/LICENSE
this_me-0.1.0.dist-info/METADATA
this_me-0.1.0.dist-info/WHEEL
this_me-0.1.0.dist-info/top_level.txt
this_me-0.1.0.dist-info/RECORD
