Metadata-Version: 2.4
Name: this-me
Version: 0.1.0
Summary: Identity Declaration of this.me.
Author: suiGn
Classifier: Programming Language :: Python :: 3
Requires-Python: >=3.6
License-File: LICENSE
Dynamic: author
Dynamic: classifier
Dynamic: description-content-type
Dynamic: license-file
Dynamic: requires-python
Dynamic: summary
